caldav_tasks_api/__init__.py
caldav_tasks_api/__main__.py
caldav_tasks_api/caldav_tasks_api.py
caldav_tasks_api/utils/__init__.py
caldav_tasks_api/utils/data.py
caldav_tasks_api/utils/logging_config.py
caldav_tasks_api-1.6.0.dist-info/licenses/LICENSE
caldav_tasks_api-1.6.0.dist-info/METADATA
caldav_tasks_api-1.6.0.dist-info/WHEEL
caldav_tasks_api-1.6.0.dist-info/entry_points.txt
caldav_tasks_api-1.6.0.dist-info/top_level.txt
caldav_tasks_api-1.6.0.dist-info/RECORD
