Metadata-Version: 2.4
Name: caldav-tasks-api
Version: 1.6.0
Summary: A Python client for CalDAV task servers, with a CLI.
Home-page: https://github.com/thiswillbeyourgithub/CaldavTasksAPI/
Author: thiswillbeyourgithub
Keywords: caldav,tasks,vtodo,todo,cli,api,nextcloud,calendar,task management
Classifier: Programming Language :: Python :: 3
Classifier: License :: OSI Approved :: GNU General Public License v3 (GPLv3)
Classifier: Operating System :: OS Independent
Classifier: Intended Audience :: Developers
Classifier: Topic :: Utilities
Requires-Python: >=3.8
License-File: LICENSE
Requires-Dist: caldav>=1.4.0
Requires-Dist: click>=8.1.8
Requires-Dist: urllib3>=2.5.0
Requires-Dist: loguru>=0.7.0
Requires-Dist: platformdirs>=3.0.0
Provides-Extra: dev
Requires-Dist: dotenv>=0.9.9; extra == "dev"
Requires-Dist: black>=25.1.0; extra == "dev"
Requires-Dist: twine>=6.1.0; extra == "dev"
Requires-Dist: build>=1.2.2.post1; extra == "dev"
Requires-Dist: bumpver>=2024.1130; extra == "dev"
Requires-Dist: pytest>=8.3.5; extra == "dev"
Requires-Dist: pre-commit>=4.2.0; extra == "dev"
Dynamic: author
Dynamic: classifier
Dynamic: description
Dynamic: description-content-type
Dynamic: home-page
Dynamic: keywords
Dynamic: license-file
Dynamic: provides-extra
Dynamic: requires-dist
Dynamic: requires-python
Dynamic: summary
